nodeconductor_jira/__init__.py
nodeconductor_jira/admin.py
nodeconductor_jira/apps.py
nodeconductor_jira/backend.py
nodeconductor_jira/executors.py
nodeconductor_jira/extension.py
nodeconductor_jira/filters.py
nodeconductor_jira/handlers.py
nodeconductor_jira/log.py
nodeconductor_jira/models.py
nodeconductor_jira/perms.py
nodeconductor_jira/serializers.py
nodeconductor_jira/urls.py
nodeconductor_jira/views.py
nodeconductor_jira/migrations/0001_initial.py
nodeconductor_jira/migrations/0002_more_issue_fields.py
nodeconductor_jira/migrations/0003_add_issue_fields.py
nodeconductor_jira/migrations/0004_project_available_for_all.py
nodeconductor_jira/migrations/__init__.py
nodeconductor_jira-0.4.0.dist-info/DESCRIPTION.rst
nodeconductor_jira-0.4.0.dist-info/METADATA
nodeconductor_jira-0.4.0.dist-info/RECORD
nodeconductor_jira-0.4.0.dist-info/WHEEL
nodeconductor_jira-0.4.0.dist-info/dependency_links.txt
nodeconductor_jira-0.4.0.dist-info/entry_points.txt
nodeconductor_jira-0.4.0.dist-info/metadata.json
nodeconductor_jira-0.4.0.dist-info/top_level.txt
